[
  {
    "_id": { "$oid": "682b00c26977bd89257c0e8e" },
    "title": "Women's Chiffon Lining Batwing Sleeve Dress",
    "description": "Women's Chiffon Dress with Flared Sleeve Lining",
    "quantity": 50,
    "sold": 10,
    "price": 850,
    "priceAfterDiscount": 850,
    "category": "68252916a68b49cb061641e8",
    "brand": "Defacto",
    "ratingsAverage": 3.1,
    "ratingsQuantity": 9
  },
  {
    "_id": { "$oid": "682b00c26977bd89257c0e8f" },
    "title": "adidas womens ULTIMASHOW Shoes",
    "description": "Jogging shoes Lace closure Water Type : Hot And Cold Textile upper REGULAR FIT",
    "quantity": 50,
    "sold": 10,
    "price": 2600,
    "priceAfterDiscount": 2600,
    "category": "68252916a68b49cb061641e8",
    "brand": "Adidas",
    "ratingsAverage": 4.4,
    "ratingsQuantity": 10
  },
  {
    "_id": { "$oid": "682b00c26977bd89257c0e90" },
    "title": "American Eagle Womens Low-Rise Baggy Wide-Leg Jean",
    "description": "WOMENS DENIM",
    "quantity": 50,
    "sold": 10,
    "price": 2700,
    "priceAfterDiscount": 2700,
    "category": "68252916a68b49cb061641e8",
    "brand": "American Eagle",
    "ratingsAverage": 3.1,
    "ratingsQuantity": 9
  },
  {
    "_id": { "$oid": "682b00c26977bd89257c0e91" },
    "title": "Dejavu womens JAL-DJTF-058 Sandal",
    "description": "Leather upper material for a luxurious look and feel",
    "quantity": 50,
    "sold": 10,
    "price": 1259,
    "priceAfterDiscount": 1259,
    "category": "68252916a68b49cb061641e8",
    "brand": "Dejavu",
    "ratingsAverage": 3.1,
    "ratingsQuantity": 9
  },
  {
    "_id": { "$oid": "682b00c26977bd89257c0e92" },
    "title": "Aldo Caraever Ladies Satchel Handbags, Khaki, Khaki",
    "description": "Bold statement design with contrasting trim and animal print accents",
    "quantity": 50,
    "sold": 10,
    "price": 5190,
    "priceAfterDiscount": 5190,
    "category": "68252916a68b49cb061641e8",
    "brand": "Aldo",
    "ratingsAverage": 3.1,
    "ratingsQuantity": 9
  },
  {
    "_id": { "$oid": "682b00c26977bd89257c0e93" },
    "title": "DeFacto Man Modern Fit Polo Neck Short Sleeve B6374AX Polo T-Shirt",
    "description": "B6374AX Polyester 100% Modern Fit Polo Neck Short Sleeve",
    "quantity": 50,
    "sold": 10,
    "price": 599,
    "priceAfterDiscount": 599,
    "category": "68252916a68b49cb061641e8",
    "brand": "Defacto",
    "ratingsAverage": 3.1,
    "ratingsQuantity": 9
  },
  {
    "_id": { "$oid": "682b00c26977bd89257c0e94" },
    "title": "DOTT JEANS WEAR Men's Relaxed Fit Jeans.",
    "description": "Relaxed Fit: These jeans offer a comfortable, relaxed fit for all-day wear.",
    "quantity": 50,
    "sold": 10,
    "price": 799,
    "priceAfterDiscount": 799,
    "category": "68252916a68b49cb061641e8",
    "brand": "DOTT JEANS WEAR",
    "ratingsAverage": 4.6,
    "ratingsQuantity": 16
  },
  {
    "_id": { "$oid": "682b00c26977bd89257c0e95" },
    "title": "Sport-Q®Fury-X Latest Model Football Shoes X Football Shoes Combining Comfort Precision and Performance Excellence in Game.",
    "description": "HIGH-QUALITY MATERIALS 】 Shoes are made of durable materials, ensuring long use and lasting efficacy.",
    "quantity": 50,
    "sold": 10,
    "price": 319,
    "priceAfterDiscount": 319,
    "category": "68252916a68b49cb061641e8",
    "brand": "Sport-Q",
    "ratingsAverage": 3.6,
    "ratingsQuantity": 22
  },
  {
    "_id": { "$oid": "682b00c26977bd89257c0e96" },
    "title": "Timberland Ek Larchmont Ftm_Chelsea, Mens Boots",
    "description": "Premium full grain leather upper with tonal sching Breathable textile lining for comfort Textile lined footbed for cushioning and support",
    "quantity": 50,
    "sold": 10,
    "price": 10499,
    "priceAfterDiscount": 10499,
    "category": "68252916a68b49cb061641e8",
    "brand": "Timberland",
    "ratingsAverage": 4.3,
    "ratingsQuantity": 57
  },
  {
    "_id": { "$oid": "682b00c26977bd89257c0e97" },
    "title": "Timberland Men's Leather Passcase Trifold Wallet Hybrid, Brown/Black, One Size",
    "description": "GENUINE LEATHER WALLET - 100% Genuine Leather wallet made from a nice soft luxury leather that is smooth to the touch and will look terrific even as it ages with everyday use includes a bonus flip out ID pocket",
    "quantity": 50,
    "sold": 10,
    "price": 1399,
    "priceAfterDiscount": 1399,
    "category": "68252916a68b49cb061641e8",
    "brand": "Timberland",
    "ratingsAverage": 4.6,
    "ratingsQuantity": 1080
  },
  {
    "_id": { "$oid": "682b00c26977bd89257c0e98" },
    "title": "LC WAIKIKI Crew Neck Girl's Shorts Pajama Set",
    "description": "WASH AT MAXIMUM 30 °C, DO NOT USE BLEACH, DO NOT TUMBLE DRY, IRON AT MEDIUM TEMPERATURE, DO NOT DRY CLEAN",
    "quantity": 50,
    "sold": 10,
    "price": 261,
    "priceAfterDiscount": 261,
    "category": "68252916a68b49cb061641e8",
    "brand": "LC WAIKIKI",
    "ratingsAverage": 4.3,
    "ratingsQuantity": 11
  },
  {
    "_id": { "$oid": "682b00c26977bd89257c0e99" },
    "title": "Kidzo Boys Pajamas",
    "description": "Comfortable to wear Made in Egypt",
    "quantity": 50,
    "sold": 10,
    "price": 580,
    "priceAfterDiscount": 580,
    "category": "68252916a68b49cb061641e8",
    "brand": "Kidzo",
    "ratingsAverage": 5.0,
    "ratingsQuantity": 3
  },
  {
    "_id": { "$oid": "682b00c26977bd89257c0e9a" },
    "title": "DeFacto Girls Cropped Fit Long Sleeve B9857A8 Denim Jacket",
    "description": "Cotton 100%",
    "quantity": 50,
    "sold": 10,
    "price": 899,
    "priceAfterDiscount": 899,
    "category": "68252916a68b49cb061641e8",
    "brand": "Defacto",
    "ratingsAverage": 5.0,
    "ratingsQuantity": 5
  },
  {
    "_id": { "$oid": "682b00c26977bd89257c0e9b" },
    "title": "Baby Boys Jacket Fashion Comfortable High Quality Plush Full Warmth Jacket for Your Baby",
    "description": "Fashionable and comfortable high quality plush jacket provides the complete warmth of your baby",
    "quantity": 50,
    "sold": 10,
    "price": 425,
    "priceAfterDiscount": 425,
    "category": "68252916a68b49cb061641e8",
    "brand": "Defacto",
    "ratingsAverage": 5.0,
    "ratingsQuantity": 1
  },
  {
    "_id": { "$oid": "682b00c26977bd89257c0e9c" },
    "title": "MIX & MAX, Ballerina Shoes, girls, Ballet Flat",
    "description": "Color: Black&Red /Size: 1-6Month/Insole Length: 11cm Made In: China Material: Synthetic Leather",
    "quantity": 50,
    "sold": 10,
    "price": 354,
    "priceAfterDiscount": 354,
    "category": "68252916a68b49cb061641e8",
    "brand": "MIX & MAX",
    "ratingsAverage": 5.0,
    "ratingsQuantity": 1
  }
]
